crose26_geodemo/__init__.py
crose26_geodemo/crose26_geodemo.py
crose26_geodemo-0.0.2.dist-info/LICENSE
crose26_geodemo-0.0.2.dist-info/METADATA
crose26_geodemo-0.0.2.dist-info/WHEEL
crose26_geodemo-0.0.2.dist-info/top_level.txt
crose26_geodemo-0.0.2.dist-info/RECORD
