Metadata-Version: 2.1
Name: crose26-geodemo
Version: 0.0.2
Summary: A Python Package for interactive mapping
Home-page: https://github.com/crose26/crose26_geodemo
Author: Caleb Rose
Author-email: crose26@vols.utk.edu
License: MIT license
Keywords: crose26_geodemo
Platform: UNKNOWN
Classifier: Development Status :: 2 - Pre-Alpha
Classifier: Intended Audience :: Developers
Classifier: License :: OSI Approved :: MIT License
Classifier: Natural Language :: English
Classifier: Programming Language :: Python :: 3
Classifier: Programming Language :: Python :: 3.5
Classifier: Programming Language :: Python :: 3.6
Classifier: Programming Language :: Python :: 3.7
Classifier: Programming Language :: Python :: 3.8
Requires-Python: >=3.5
